sudoku/__init__.py
sudoku/sudoku_oop.py
Sudoku_DCHEQUER-0.0.5.dist-info/LICENSE
Sudoku_DCHEQUER-0.0.5.dist-info/METADATA
Sudoku_DCHEQUER-0.0.5.dist-info/WHEEL
Sudoku_DCHEQUER-0.0.5.dist-info/top_level.txt
Sudoku_DCHEQUER-0.0.5.dist-info/RECORD
