Metadata-Version: 2.1
Name: Sudoku-DCHEQUER
Version: 0.0.5
Summary: An Object Oriented Sudoku Game Generator
Home-page: https://github.com/dchequer/sudoku_dchequer
Author: Diego Chequer
Author-email: millychequer@gmail.com
License: UNKNOWN
Project-URL: Bug Tracker, https://github.com/dchequer/sudoku_dchequer/issues
Platform: UNKNOWN
Classifier: Programming Language :: Python :: 3
Classifier: License :: OSI Approved :: MIT License
Classifier: Operating System :: OS Independent
Requires-Python: >=3.6
License-File: LICENSE
